main.py
source_fleetio/__init__.py
source_fleetio/manifest.yaml
source_fleetio/run.py
source_fleetio/schemas/contacts.json
source_fleetio/schemas/expense_entries.json
source_fleetio/schemas/fuel_entries.json
source_fleetio/schemas/issues.json
source_fleetio/schemas/parts.json
source_fleetio/schemas/purchase_orders.json
source_fleetio/schemas/service_entries.json
source_fleetio/schemas/submitted_inspection_forms.json
source_fleetio/schemas/vehicle_assignments.json
source_fleetio/schemas/vehicles.json
source_fleetio/source.py
airbyte_source_fleetio-0.1.11.dist-info/METADATA
airbyte_source_fleetio-0.1.11.dist-info/WHEEL
airbyte_source_fleetio-0.1.11.dist-info/entry_points.txt
airbyte_source_fleetio-0.1.11.dist-info/RECORD
